pwed_cdk/__init__.py
pwed_cdk/py.typed
pwed_cdk/_jsii/__init__.py
pwed_cdk/_jsii/pwed-cdk@0.0.68.jsii.tgz
pwed_cdk/bastion/__init__.py
pwed_cdk/static_site/__init__.py
pwed_cdk/ttl/__init__.py
pwed_cdk-0.0.68.dist-info/LICENSE
pwed_cdk-0.0.68.dist-info/METADATA
pwed_cdk-0.0.68.dist-info/WHEEL
pwed_cdk-0.0.68.dist-info/top_level.txt
pwed_cdk-0.0.68.dist-info/RECORD
